prcerlc/__init__.py
prcerlc/client.py
prcerlc/logs.py
prcerlc/players.py
prcerlc/server.py
prcerlc/vehicles.py
prcerlc-0.1.0.dist-info/licenses/LICENSE
prcerlc-0.1.0.dist-info/METADATA
prcerlc-0.1.0.dist-info/WHEEL
prcerlc-0.1.0.dist-info/top_level.txt
prcerlc-0.1.0.dist-info/RECORD
