Metadata-Version: 2.4
Name: prcerlc
Version: 0.1.0
Summary: Python API wrapper for Emergency Response: Liberty County (PRC)
Home-page: https://github.com/GijsRibberink/prcerlc
Author: Gijs Ribberink
Author-email: Gijs Ribberink <gijs.ribberink@kpnmail.nl>
Classifier: Programming Language :: Python :: 3
Classifier: License :: OSI Approved :: MIT License
Classifier: Operating System :: OS Independent
Requires-Python: >=3.8
License-File: LICENSE
Requires-Dist: requests>=2.28.0
Dynamic: author
Dynamic: home-page
Dynamic: license-file
Dynamic: requires-python
